{"family":"ENERGIE_SOLAIRE","references":{"PV_PANEL_550W":{"price_min":120000,"price_max":280000,"currency":"FCFA","unit":"U","quality":"MEDIUM","region":"CENTRAL_AFRICA","importability":"HIGH","logistic_weight":"MEDIUM"},"SOLAR_INVERTER_10KW":{"price_min":1800000,"price_max":8500000,"currency":"FCFA","unit":"U","quality":"MEDIUM","region":"CENTRAL_AFRICA","importability":"HIGH","logistic_weight":"MEDIUM"},"LITHIUM_BATTERY_5KWH":{"price_min":1800000,"price_max":7500000,"currency":"FCFA","unit":"U","quality":"MEDIUM","region":"CENTRAL_AFRICA","importability":"HIGH","logistic_weight":"HEAVY"}}}
